code/__init__.py
code/class.py
pkg_temp-0.1.0.dist-info/LICENSE.txt
pkg_temp-0.1.0.dist-info/METADATA
pkg_temp-0.1.0.dist-info/WHEEL
pkg_temp-0.1.0.dist-info/top_level.txt
pkg_temp-0.1.0.dist-info/RECORD
