Metadata-Version: 2.1
Name: pkg-temp
Version: 0.1.0
Summary: A small example package
Home-page: https://github.com/
Author: Example Author
Author-email: author@example.com
License: UNKNOWN
Platform: UNKNOWN
Classifier: Programming Language :: Python :: 3
Classifier: License :: OSI Approved :: MIT License
Classifier: Operating System :: OS Independent
Requires-Python: >=3.6
